redisdatabus/__init__.py
redisdatabus/bus.py
carpi_redisdatabus-0.2.0.dist-info/LICENSE
carpi_redisdatabus-0.2.0.dist-info/METADATA
carpi_redisdatabus-0.2.0.dist-info/WHEEL
carpi_redisdatabus-0.2.0.dist-info/top_level.txt
carpi_redisdatabus-0.2.0.dist-info/RECORD
