Metadata-Version: 2.1
Name: carpi-redisdatabus
Version: 0.2.0
Summary: Redis Data Bus (inspired by CAN-BUS, developed for CarPi)
Home-page: https://github.com/rGunti/CarPi-RedisDataBus
Author: Raphael "rGunti" Guntersweiler
Author-email: raphael@rgunti.ch
License: MIT
Keywords: carpi redis data bus
Platform: UNKNOWN
Classifier: Development Status :: 3 - Alpha
Classifier: License :: OSI Approved :: MIT License
Classifier: Programming Language :: Python :: 3.6
Requires-Dist: carpi-commons
Requires-Dist: redis
Requires-Dist: tzlocal
Requires-Dist: pytz
Requires-Dist: wheel
